<?xml version="1.0"?>
<ls>
<l><name>DIVISION</name><c>4021,1610 4106,1604 4326,1575 4414,1569 4458,1571 4501,1577 4632,1601 4809,1620 4937,1651 4980,1659 5023,1662 5067,1658 5154,1639 5287,1620 5331,1617 5374,1618 5418,1629 5451,1650 5477,1677 5498,1707 5511,1737 5507,1768 5495,1801 5488,1834 5517,1855 5556,1874 5587,1898 5615,1923 5639,1950 5657,1980 5679,2042 5691,2107 5684,2172 5696,2202 5725,2230 5764,2244 5807,2249 5852,2252 6125,2253 6215,2250 6304,2243 6436,2222 6488,2211 </c></l>
<l><name>SECTION</name><c>3021,4865 2983,4850 2912,4806 2849,4757 2826,4730 2820,4699 2825,4664 2822,4632 2797,4607 2762,4586 2682,4548 2642,4530 2555,4501 2515,4485 2483,4464 2462,4435 2454,4401 2457,4368 2472,4339 2542,4253 2573,4191 2591,4127 2591,4096 2569,4016 </c></l>
<l><name>SECTION</name><c>7934,1204 7786,1232 7700,1245 7612,1253 7522,1256 7478,1255 7434,1251 7347,1238 7261,1218 7220,1205 7144,1174 7071,1136 7002,1094 6940,1048 6887,998 6841,943 6721,769 6450,438 6215,129 6148,46 6100,-10 </c></l>
</ls>